ddeutil/model/__about__.py
ddeutil/model/__base.py
ddeutil/model/__enums.py
ddeutil/model/__init__.py
ddeutil/model/__types.py
ddeutil/model/action.py
ddeutil/model/conn.py
ddeutil/model/const.py
ddeutil/model/dtype.py
ddeutil/model/lineage.py
ddeutil/model/settings.py
ddeutil/model/utils.py
ddeutil/model/datasets/__init__.py
ddeutil/model/datasets/col.py
ddeutil/model/datasets/db.py
ddeutil/model/datasets/file.py
ddeutil_model-0.0.4.dist-info/LICENSE
ddeutil_model-0.0.4.dist-info/METADATA
ddeutil_model-0.0.4.dist-info/WHEEL
ddeutil_model-0.0.4.dist-info/top_level.txt
ddeutil_model-0.0.4.dist-info/RECORD
