Metadata-Version: 2.1
Name: ddeutil-model
Version: 0.0.4
Summary: Data Developer & Engineer Model Utility Objects
Author-email: ddeutils <korawich.anu@gmail.com>
License: MIT
Project-URL: Homepage, https://github.com/ddeutils/ddeutil-model/
Project-URL: Source Code, https://github.com/ddeutils/ddeutil-model/
Keywords: data,model,utility,pipeline
Classifier: Topic :: Utilities
Classifier: Natural Language :: English
Classifier: Development Status :: 3 - Alpha
Classifier: Intended Audience :: Developers
Classifier: Operating System :: OS Independent
Classifier: Programming Language :: Python
Classifier: Programming Language :: Python :: 3 :: Only
Classifier: Programming Language :: Python :: 3.9
Classifier: Programming Language :: Python :: 3.10
Classifier: Programming Language :: Python :: 3.11
Classifier: Programming Language :: Python :: 3.12
Requires-Python: >=3.9.13
License-File: LICENSE
Requires-Dist: ddeutil
Requires-Dist: tzdata
Requires-Dist: pydantic ==2.7.1
